dynamics/__init__.py
dynamics/apis/__init__.py
dynamics/apis/accounts.py
dynamics/apis/api_base.py
dynamics/apis/attachments.py
dynamics/apis/bank_accounts.py
dynamics/apis/companies.py
dynamics/apis/dimensions.py
dynamics/apis/employees.py
dynamics/apis/environments.py
dynamics/apis/invoice_line_items.py
dynamics/apis/invoices.py
dynamics/apis/journal.py
dynamics/apis/journal_line_items.py
dynamics/apis/locations.py
dynamics/apis/vendors.py
dynamics/core/__init__.py
dynamics/core/client.py
dynamics/exceptions/__init__.py
dynamics/exceptions/dynamics_exceptions.py
ms_dynamics_business_central_sdk-1.7.0.dist-info/LICENSE
ms_dynamics_business_central_sdk-1.7.0.dist-info/METADATA
ms_dynamics_business_central_sdk-1.7.0.dist-info/WHEEL
ms_dynamics_business_central_sdk-1.7.0.dist-info/top_level.txt
ms_dynamics_business_central_sdk-1.7.0.dist-info/RECORD
