Metadata-Version: 2.2
Name: ms-dynamics-business-central-sdk
Version: 1.7.0
Summary: Python SDK for accessing Dynamics APIs
Home-page: https://github.com/fylein/ms-dynamics-business-central-sdk-py
Author: Shwetabh Kumar
Author-email: shwetabh.kumar@fyle.in
License: MIT
Keywords: dynamics,business-central,ms,ms-dynamics-business-central,fyle,api,python,sdk
Classifier: Topic :: Internet :: WWW/HTTP
Classifier: Intended Audience :: Developers
Classifier: Programming Language :: Python :: 3
Classifier: License :: OSI Approved :: MIT License
Classifier: Operating System :: OS Independent
License-File: LICENSE
Requires-Dist: requests
Dynamic: author
Dynamic: author-email
Dynamic: classifier
Dynamic: description
Dynamic: description-content-type
Dynamic: home-page
Dynamic: keywords
Dynamic: license
Dynamic: requires-dist
Dynamic: summary
